resamp/__init__.py
resamp/resamp.py
resamp-1.8.1.dist-info/licenses/LICENSE
resamp-1.8.1.dist-info/METADATA
resamp-1.8.1.dist-info/WHEEL
resamp-1.8.1.dist-info/top_level.txt
resamp-1.8.1.dist-info/RECORD
