Metadata-Version: 2.4
Name: resamp
Version: 1.8.1
Summary: A custom statistics library of resampling technqiues for chi-abs, boostrapping analysis and other statistical functions.
Home-page: https://github.com/vishanth10/resamp.git
Author: Vishanth Hari Raj Balasubramanian
Author-email: rbvish1007@gmail.com
Keywords: resampling techniques,resample,chi-abs,power analysis,relative risk,statistics,resampling chi-abs analysis
Classifier: Development Status :: 3 - Alpha
Classifier: Intended Audience :: Education
Classifier: License :: OSI Approved :: MIT License
Classifier: Programming Language :: Python :: 3
Classifier: Programming Language :: Python :: 3.7
Classifier: Programming Language :: Python :: 3.8
Classifier: Programming Language :: Python :: 3.9
License-File: LICENSE
Requires-Dist: numpy>=1.18.5
Requires-Dist: pandas>=1.0.5
Requires-Dist: scipy>=1.5.0
Requires-Dist: matplotlib>=3.2.2
Requires-Dist: statsmodels>=0.11.1
Requires-Dist: scikit-learn>=0.23.1
Requires-Dist: seaborn>=0.10
Dynamic: author
Dynamic: author-email
Dynamic: classifier
Dynamic: description
Dynamic: description-content-type
Dynamic: home-page
Dynamic: keywords
Dynamic: license-file
Dynamic: requires-dist
Dynamic: summary
